cyclonedx_lint/__init__.py
cyclonedx_lint/__main__.py
cyclonedx_lint/cli.py
cyclonedx_lint/lint.py
test/__init__.py
test/conftest.py
test/context.py
test/test_cli.py
test/test_lint.py
cyclonedx_lint-2022.7.17.dist-info/LICENSE
cyclonedx_lint-2022.7.17.dist-info/METADATA
cyclonedx_lint-2022.7.17.dist-info/WHEEL
cyclonedx_lint-2022.7.17.dist-info/entry_points.txt
cyclonedx_lint-2022.7.17.dist-info/top_level.txt
cyclonedx_lint-2022.7.17.dist-info/RECORD
